stundrg_check_os_ver-0.4.3.dist-info/METADATA
stundrg_check_os_ver-0.4.3.dist-info/WHEEL
stundrg_check_os_ver-0.4.3.dist-info/entry_points.txt
stundrg_check_os_ver/__init__.py
stundrg_check_os_ver/hi.py
stundrg_check_os_ver/osver.py
stundrg_check_os_ver-0.4.3.dist-info/RECORD
