Metadata-Version: 2.1
Name: stundrg-check-os-ver
Version: 0.4.3
Summary: Utility that checks the name and version of the operating system.
Author-Email: khr0106 <kanghr990106@gmail.com>
License: MIT
Project-URL: Homepage, https://github.com/stundrg/stundrg-check-os-ver
Project-URL: Issues, https://github.com/stundrg/stundrg-stundrg-check-os-ver/issues
Requires-Python: >=3.10
Requires-Dist: check-os-ver>=0.2.1
Requires-Dist: hj-check-os-version>=0.3.4
Requires-Dist: lucas-check-os-ver>=0.2.1
Requires-Dist: jacob-os-version-check>=0.2.4
Requires-Dist: cho-check-os-ver>=0.2.3
Requires-Dist: seo-check-os-version>=0.2.0
Requires-Dist: nunininu-check-os-ver>=0.3.0
Requires-Dist: president-speech>=0.9.1
